copspy/__init__.py
copspy/api_urls.py
copspy/apierror.py
copspy/get_profile.py
copspy/get_server_status.py
u_copsapi-0.2.3.dist-info/LICENSE.txt
u_copsapi-0.2.3.dist-info/METADATA
u_copsapi-0.2.3.dist-info/WHEEL
u_copsapi-0.2.3.dist-info/top_level.txt
u_copsapi-0.2.3.dist-info/RECORD
