Metadata-Version: 2.1
Name: u-copsapi
Version: 0.2.3
Summary: a fan made python API wrapper for the c-ops public api
Home-page: https://github.com/Kitsune-San/cops.py
Author: Kitsune
Author-email: kitsune@yokaigroup.gg
License: MIT
Keywords: cops,api,wrapper,apiwrapper,python,c-ops
License-File: LICENSE.txt
Requires-Dist: requests
Requires-Dist: colorama
